anime365/__init__.py
anime365/constants.py
anime365/client/__init__.py
anime365/client/anime.py
anime365/client/auth.py
anime365/client/base.py
anime365/client/embed.py
anime365/client/episodes.py
anime365/client/translations.py
anime365/exceptions/__init__.py
anime365/exceptions/api.py
anime365/exceptions/auth.py
anime365/exceptions/base.py
anime365/exceptions/validation.py
anime365/models/__init__.py
anime365/models/anime.py
anime365/models/common.py
anime365/models/episodes.py
anime365/models/translations.py
anime365/utils/__init__.py
anime365/utils/helpers.py
anime365/utils/validators.py
anime365-1.0.0.dist-info/licenses/LICENSE
anime365-1.0.0.dist-info/METADATA
anime365-1.0.0.dist-info/WHEEL
anime365-1.0.0.dist-info/top_level.txt
anime365-1.0.0.dist-info/RECORD
