Metadata-Version: 2.4
Name: anime365
Version: 1.0.0
Summary: Асинхронная Python библиотека для работы с API anime365 (smotret-anime)
Author-email: ragedrugg <rage@dvxchsquad.dev>
Maintainer-email: ragedrugg <rage@dvxchsquad.dev>
License: MIT
Project-URL: Homepage, https://github.com/ragedrugg/anime365
Project-URL: Documentation, https://github.com/ragedrugg/anime365#readme
Project-URL: Repository, https://github.com/ragedrugg/anime365
Project-URL: Issues, https://github.com/ragedrugg/anime365/issues
Keywords: anime,api,wrapper,async,aiohttp,smotret-anime,anime365
Classifier: Development Status :: 5 - Production/Stable
Classifier: Intended Audience :: Developers
Classifier: License :: OSI Approved :: MIT License
Classifier: Operating System :: OS Independent
Classifier: Programming Language :: Python :: 3
Classifier: Programming Language :: Python :: 3.7
Classifier: Programming Language :: Python :: 3.8
Classifier: Programming Language :: Python :: 3.9
Classifier: Programming Language :: Python :: 3.10
Classifier: Programming Language :: Python :: 3.11
Classifier: Programming Language :: Python :: 3.12
Classifier: Topic :: Internet :: WWW/HTTP :: Dynamic Content
Classifier: Topic :: Software Development :: Libraries :: Python Modules
Classifier: Topic :: Multimedia :: Video
Requires-Python: >=3.7
License-File: LICENSE
Requires-Dist: aiohttp>=3.8.0
Requires-Dist: pydantic>=2.0.0
Provides-Extra: dev
Requires-Dist: pytest>=6.0; extra == "dev"
Requires-Dist: pytest-asyncio>=0.18.0; extra == "dev"
Requires-Dist: black>=22.0; extra == "dev"
Requires-Dist: flake8>=4.0; extra == "dev"
Requires-Dist: mypy>=0.950; extra == "dev"
Dynamic: license-file
